chess_stats/__init__.py
chess_stats/chess_stats.py
chess_stats/console.py
chess_stats/models/__init__.py
chess_stats/models/annual_summary.py
chess_stats/models/chess_dot_com_client.py
chess_stats/models/game.py
chess_stats/models/player.py
chess_stats-0.1.1.dist-info/entry_points.txt
chess_stats-0.1.1.dist-info/WHEEL
chess_stats-0.1.1.dist-info/METADATA
chess_stats-0.1.1.dist-info/RECORD
