Metadata-Version: 2.1
Name: chess-stats
Version: 0.1.1
Summary: A simple command-line tool that graphs Chess.com game stats
License: MIT
Author: julianmclain
Author-email: julianrmclain@gmail.com
Requires-Python: >=3.7,<4.0
Classifier: License :: OSI Approved :: MIT License
Classifier: Programming Language :: Python :: 3
Classifier: Programming Language :: Python :: 3.7
Classifier: Programming Language :: Python :: 3.8
Requires-Dist: click (>=7.1.2,<8.0.0)
Requires-Dist: requests (>=2.24.0,<3.0.0)
